{
  "id": "10428478",
  "title": "Muv-Luv Alternative Total Eclipse",
  "allTitle": "Muv-Luv Alternative Total Eclipse トータル・イクリプス",
  "year": "2012",
  "info": {
    "导演": "稻垣隆行",
    "编剧": "山口宏",
    "主演": "小野大辅 / 中原麻衣 / 生天目仁美 / 能登麻美子 / 野川樱 / 杉田智和",
    "类型": "科幻 / 动画",
    "首播": "2012-07-01(日本)",
    "集数": "24",
    "又名": "Muv-Luv ATE"
  },
  "rating": {
    "分数": "6.2",
    "人数": "767",
    "5星": "10.0%",
    "4星": "19.7%",
    "3星": "44.5%",
    "2星": "20.6%",
    "1星": "5.2%"
  },
  "summary": "Muv-Luv ATE全名为《Muv-Luv Alternative Total eclipse 》，全集动画片改编自《Muv-Luv Alternative》的外传小说。故事的时间设定在西元2001年，由于人类遭到地球外起源种(联合国称其为BETA)的侵略，正面临灭亡的危机，因此人类开始了先进战术机技术开发计划“XFJ计划”，各个国家均派遣了专门人员参与其中，该作讲述的就是这些被派遣过来的人员之间的故事。\n                                    \n                                　　（有虫子吃掉妹纸情节,反差极大,请谨慎观看.）",
  "comments": [
    " 冲着第二话去看的（你），前两话只是序章，正片还没开始~感觉制作组经费不是非常多，如果一心追求华丽的画面去看一定会很失望的，但是总体来说还是一部不错的SF动画~推荐给喜欢这一类型的同学~最后，打分的各位，别只看了点皮毛就急着乱喊渣作好吗？！\n        ",
    " 里面的妹子领便当领的太happy！！！！\n        ",
    " 画质渣到5分钟关闭~！\n        ",
    " 追了\n        "
  ],
  "reviews": [
    {
      "title": "MUV本篇之所以難以動畫化的理由",
      "html": [
        "\n      1.原作和動畫上的差異，要把本篇的張力展現出來至少需要拿出像蒼穹のファフナー EXODUS那樣的製作水準，問題是ATE除了3D模組及格外很多畫面表現根本就跟製作差勁的H動畫差不多，還時常人物作畫崩壞。",
        "",
        "",
        "2.劇情問題，前兩回外星生物讓一堆妹子吃便當過後莫名其妙的政治戲和福利戀愛劇太多嚴重拖垮故事節奏，與本傳相關的科技設定又多又臭又長，在說明設定進入正戲前觀眾的興趣都被過長的無謂橋段給磨光，更慘的是為了宣傳遊戲，動畫不打算做出原作應該有的後半段，沒有做出後面的結局估計是不會補坑了。\n    "
      ]
    },
    {
      "title": "看不下去，",
      "html": [
        "\n      前两集在炼狱般的黑暗里最后得以生存的女主角就给按到这么无厘头的世界里？和所有其他人都一样围着男主角转，彻底毁了啊。制作方让她的眼睛颜色更好看了代表出一个什么样的心灵啊。",
        "",
        "而且不管什么设定，什么背景什么人物，在动漫里的格调和气质真都差不多，什么尼泊尔瑞典的都去死吧，都是日本动漫玩偶而已。",
        "",
        "感觉后22集压缩成八九集集左右，放在前面，然后前两集里再扩出部分时间让这后面的人一一去死的话可能风格要高尚很多。12集够了，又臭又长我跳着看都不耐烦。\n    "
      ]
    }
  ]
}