{
  "id": "1867421",
  "title": "头文字D 第二季",
  "allTitle": "头文字D 第二季 頭文字D Second Stage",
  "year": "1999",
  "info": {
    "导演": "Shin-ichi Masaki",
    "编剧": "重野秀一(原作) / 戸田博史",
    "主演": "三木真一郎 / 岩田光央 / 石冢运升 / 川澄绫子 / 矢尾一树 / 西村知道 / 子安武人 / 关智一",
    "类型": "喜剧 / 动作 / 动画",
    "首播": "1999-10-15(日本)",
    "季数": "2",
    "集数": "13",
    "单集片长": "27分钟",
    "又名": "头文字D：Second Stage / Initial D"
  },
  "rating": {
    "分数": "8.7",
    "人数": "2931",
    "5星": "47.6%",
    "4星": "41.8%",
    "3星": "10.0%",
    "2星": "0.5%",
    "1星": "0.0%"
  },
  "summary": "藤原拓海由于不败的战绩，必然会受到新的挑战。\n                                    \n                                　　《头文字D》的第二部着重突出拓海的成长，当然不乏激烈的挑战。最经典的要数赤诚和依吕波山路两位老大的比拼。年轻的拓海在爱情上触了礁，在输给帝王车队的lanEvo 3后，拓海遇到了人生的挫折，对自己和AE86产生了怀疑，AE86真的有足够的实力吗？\n                                    \n                                　　AE86的重生来自拓海的爸爸文太，他为AE86改装了赛车用引擎。同时，拓海遇到了同样是AE86的强劲对手秋山涉。有意思的是比赛规则是在同一赛道两车来回追赶，直到其中之一能超越对方为止，既要技术又考耐力。胜利让拓海继续接受这辆AE86和重拾信心回到车手的生涯。",
  "comments": [
    " 小时候只看过第一部，长这么大第二部依然好看\n        ",
    " 画风作了修改，人物依旧还是保留一贯的2D，赛车的镜头还是紧张紧凑，很带感。第二部是86在群马崭露头角的开始，EVO对阵FC，特雷诺对雷宾都是重头戏，让人血脉喷张。为下一部的征程作了铺垫。整个系列的爱情都显得忧郁凄冷，主线情节明显疲软，让人摸不到头脑，七年后才知道夏树是跟叔叔乱伦。\n        ",
    " 86的重生\n                \n                \n        ",
    " 不在赛车界，似乎真的很难理解他们的心境；作为旁人看了，也就是让自己稍微兴奋与热血吧\n        "
  ],
  "reviews": [
    {
      "title": "第二季比赛列表",
      "html": [
        "\n               ",
        "",
        "2     岩城清次  vs  藤原拓海、、、、秋名山、、、、让步赛，拓海胜",
        "",
        "（EMPEROR)",
        "",
        "3     须藤京一  vs  藤原拓海 、、、、赤城 、、、、让步赛，京一胜（86引擎爆缸）",
        "",
        "（EMPEROR)   ",
        "",
        "4     须藤京一  vs  高桥凉介、、、 、 赤城 、、、、、凉介胜",
        "",
        "（EMPEROR) (REDSUNS)",
        "",
        "6        秋山涉  vs  藤原拓海   、、、埼玉、正丸山道 、、 拓海第五局胜",
        "",
        "     ",
        "",
        "     ",
        "",
        "     今天我一脚油门踩到二十迈，竟然就这么燃起来了。",
        "",
        "     毕竟第一次坐在驾驶室。",
        "",
        "",
        "      ",
        "",
        "    \n    "
      ]
    }
  ]
}